continuous_threading/__init__.py
continuous_threading/__meta__.py
continuous_threading/fix_threading_shutdown.py
continuous_threading/safe_multiprocessing.py
continuous_threading/safe_threading.py
continuous_threading/threading_utils.py
continuous_threading/timer_utils.py
continuous_threading-2.0.6.dist-info/LICENSE
continuous_threading-2.0.6.dist-info/METADATA
continuous_threading-2.0.6.dist-info/WHEEL
continuous_threading-2.0.6.dist-info/top_level.txt
continuous_threading-2.0.6.dist-info/RECORD
