Metadata-Version: 2.1
Name: continuous-threading
Version: 2.0.6
Summary: Library to help manage threads that run continuously for a long time.
Home-page: https://github.com/justengel/continuous_threading
Author: Justin Engel
Author-email: jtengel08@gmail.com
License: MIT
Download-URL: https://github.com/justengel/continuous_threading/archive/v2.0.6.tar.gz
Keywords: threading continuous pausable
Platform: any
Classifier: Programming Language :: Python
Classifier: Programming Language :: Python :: 3
Classifier: Operating System :: OS Independent
License-File: LICENSE
Requires-Dist: psutil (>=5.4.0)
